.coveragerc
.editorconfig
.flake8
.gitignore
.pre-commit-config.yaml
LICENSE
MANIFEST.in
Makefile
README.md
environment.yml
mkdocs.yml
pytest.ini
requirements.txt
setup.py
.github/PULL_REQUEST_TEMPLATE.md
.github/dependabot.yml
.github/workflows/gh-pages.yml
.github/workflows/run_tests.yml
data/2-akker.sig
data/2.fa.gz
data/47-os185.sig
data/47.fa.gz
data/63-os223.sig
data/63.fa.gz
data/README.md
data/acido-chunk1.fa.gz
data/acido-chunk2.fa.gz
data/acido-chunk3.fa.gz
data/acido-chunk4.fa.gz
data/acido-chunk5.fa.gz
data/acido-chunk6.fa.gz
data/acido-chunk7.fa.gz
data/acido-chunk8.fa.gz
data/acido-short.fa
data/acido.fa.gz
data/bcalm-BROKEN.dory.k21.unitigs.fa
data/bcalm.dory.k21.unitigs.fa
data/dory-dna-translate-query.fa
data/dory-head.fa
data/dory-k21-hashval-queries.txt
data/dory-k31-hashval-queries.txt
data/dory-prot-query.faa
data/dory-subset.fa
data/dory-subset.fq
data/dory-subset.fq.sig
data/podar-lineage.csv
data/random-query-nomatch.fa
data/shew-os223-200k.fa
data/shew-os223-200k.fa.sig
data/tr-1.fa
data/tr-2.fa
data/tr-cross-rev.fa
data/tr-cross.fa
data/tr-small.fa
data/tr-vsmall.fa
data/twofoo-genes.fa.gz
data/twofoo-k31-hashval-queries.txt
data/twofoo-k51-hashval-queries.txt
data/mircea-sigs/cmd.sh
data/mircea-sigs/mircea-rm18.0.fa.sig
data/mircea-sigs/mircea-rm18.1.fa.sig
data/mircea-sigs/mircea-rm18.10.fa.sig
data/mircea-sigs/mircea-rm18.11.fa.sig
data/mircea-sigs/mircea-rm18.12.fa.sig
data/mircea-sigs/mircea-rm18.13.fa.sig
data/mircea-sigs/mircea-rm18.14.fa.sig
data/mircea-sigs/mircea-rm18.15.fa.sig
data/mircea-sigs/mircea-rm18.16.fa.sig
data/mircea-sigs/mircea-rm18.17.fa.sig
data/mircea-sigs/mircea-rm18.18.fa.sig
data/mircea-sigs/mircea-rm18.19.fa.sig
data/mircea-sigs/mircea-rm18.2.fa.sig
data/mircea-sigs/mircea-rm18.20.fa.sig
data/mircea-sigs/mircea-rm18.21.fa.sig
data/mircea-sigs/mircea-rm18.22.fa.sig
data/mircea-sigs/mircea-rm18.23.fa.sig
data/mircea-sigs/mircea-rm18.24.fa.sig
data/mircea-sigs/mircea-rm18.25.fa.sig
spacegraphcats.egg-info/PKG-INFO
spacegraphcats.egg-info/SOURCES.txt
spacegraphcats.egg-info/dependency_links.txt
spacegraphcats.egg-info/entry_points.txt
spacegraphcats.egg-info/requires.txt
spacegraphcats.egg-info/top_level.txt
