Metadata-Version: 2.1
Name: spacegraphcats
Version: 2.1.2
Summary: tools for biological assembly graph neighborhood analysis
Home-page: https://github.com/spacegraphcats/spacegraphcats
Author: C. Titus Brown, Dominik Moritz, Michael P. O'Brien, Felix Reidl, Taylor Reiter, Yosuke Mizutani, and Blair D. Sullivan
Author-email: titus@idyll.org,blair.d.sullivan@gmail.com
License: BSD 3-clause
Platform: UNKNOWN
Classifier: Environment :: Console
Classifier: Environment :: MacOS X
Classifier: Intended Audience :: Science/Research
Classifier: License :: OSI Approved :: BSD License
Classifier: Natural Language :: English
Classifier: Operating System :: POSIX :: Linux
Classifier: Operating System :: MacOS :: MacOS X
Classifier: Programming Language :: C++
Classifier: Programming Language :: Python :: 3.7
Classifier: Programming Language :: Python :: 3.8
Classifier: Programming Language :: Python :: 3.9
Classifier: Topic :: Scientific/Engineering :: Bio-Informatics
License-File: LICENSE
